item_tracking/__init__.py
item_tracking/item.py
item_tracking/tracker.py
item_tracking-1.0.10.dist-info/LICENSE
item_tracking-1.0.10.dist-info/METADATA
item_tracking-1.0.10.dist-info/WHEEL
item_tracking-1.0.10.dist-info/top_level.txt
item_tracking-1.0.10.dist-info/RECORD
