Metadata-Version: 2.1
Name: item-tracking
Version: 1.0.10
Summary: A tracking algorithm for general purpose
Home-page: https://github.com/fannibal/item_tracking.git
Author: Fabrice POIRIER
Author-email: fabrice.poirier@ensta-bretagne.org
License: UNKNOWN
Platform: UNKNOWN
Classifier: Programming Language :: Python :: 2.7
Classifier: Programming Language :: Python :: 3
Classifier: License :: OSI Approved :: Apache Software License
Classifier: Operating System :: POSIX
